README.md
setup.py
nonadateconverter/__init__.py
nonadateconverter/version.py
nonadateconverter.egg-info/PKG-INFO
nonadateconverter.egg-info/SOURCES.txt
nonadateconverter.egg-info/dependency_links.txt
nonadateconverter.egg-info/requires.txt
nonadateconverter.egg-info/top_level.txt
nonadateconverter/converter/__init__.py
nonadateconverter/converter/gregorian.py
nonadateconverter/converter/hijri.py
nonadateconverter/converter/jalali.py
nonadateconverter/core/__init__.py
nonadateconverter/core/base.py